README.md
setup.cfg
setup.py
hcmidiaSync/__init__.py
hcmidiaSync/hcmidiaSync.py
hcmidiaSync.egg-info/PKG-INFO
hcmidiaSync.egg-info/SOURCES.txt
hcmidiaSync.egg-info/dependency_links.txt
hcmidiaSync.egg-info/requires.txt
hcmidiaSync.egg-info/top_level.txt
hcmidiaSync/bin/hcmidia-clean
hcmidiaSync/bin/hcmidia-schedule
hcmidiaSync/bin/hcmidia-sync