Metadata-Version: 1.0
Name: hcmidiaSync
Version: 0.35
Summary: Sync videos
Home-page: https://temoque.com.br/
Author: Carla Dias
Author-email: carladias@temoque.com.br
License: MIT License
Keywords: sync videos screenly
Platform: UNKNOWN
